[{"frame_index": 98854, "path": "data/keyframes/L12_V006/298.jpg", "video": "L12_V006", "score": 0.3594103157520294}, {"frame_index": 98853, "path": "data/keyframes/L12_V006/297.jpg", "video": "L12_V006", "score": 0.35784193873405457}, {"frame_index": 9731, "path": "data/keyframes/L02_V006/220.jpg", "video": "L02_V006", "score": 0.3570428490638733}, {"frame_index": 9735, "path": "data/keyframes/L02_V006/224.jpg", "video": "L02_V006", "score": 0.34724196791648865}, {"frame_index": 61775, "path": "data/keyframes/L08_V008/306.jpg", "video": "L08_V008", "score": 0.3467474579811096}, {"frame_index": 66557, "path": "data/keyframes/L08_V025/016.jpg", "video": "L08_V025", "score": 0.34173229336738586}, {"frame_index": 9729, "path": "data/keyframes/L02_V006/218.jpg", "video": "L02_V006", "score": 0.34078410267829895}, {"frame_index": 64730, "path": "data/keyframes/L08_V018/311.jpg", "video": "L08_V018", "score": 0.3385283052921295}, {"frame_index": 64729, "path": "data/keyframes/L08_V018/310.jpg", "video": "L08_V018", "score": 0.3382371962070465}, {"frame_index": 9737, "path": "data/keyframes/L02_V006/226.jpg", "video": "L02_V006", "score": 0.3372318744659424}, {"frame_index": 60915, "path": "data/keyframes/L08_V005/318.jpg", "video": "L08_V005", "score": 0.3359319567680359}, {"frame_index": 98843, "path": "data/keyframes/L12_V006/287.jpg", "video": "L12_V006", "score": 0.33559051156044006}, {"frame_index": 62945, "path": "data/keyframes/L08_V012/239.jpg", "video": "L08_V012", "score": 0.3354511260986328}, {"frame_index": 40597, "path": "data/keyframes/L05_V028/170.jpg", "video": "L05_V028", "score": 0.33519455790519714}, {"frame_index": 9728, "path": "data/keyframes/L02_V006/217.jpg", "video": "L02_V006", "score": 0.3349531888961792}, {"frame_index": 104053, "path": "data/keyframes/L12_V022/275.jpg", "video": "L12_V022", "score": 0.3344781696796417}, {"frame_index": 25290, "path": "data/keyframes/L04_V002/289.jpg", "video": "L04_V002", "score": 0.33378350734710693}, {"frame_index": 9725, "path": "data/keyframes/L02_V006/214.jpg", "video": "L02_V006", "score": 0.33307236433029175}, {"frame_index": 102798, "path": "data/keyframes/L12_V018/388.jpg", "video": "L12_V018", "score": 0.3319867253303528}, {"frame_index": 70389, "path": "data/keyframes/L09_V007/125.jpg", "video": "L09_V007", "score": 0.33138811588287354}, {"frame_index": 102788, "path": "data/keyframes/L12_V018/378.jpg", "video": "L12_V018", "score": 0.33103853464126587}, {"frame_index": 9998, "path": "data/keyframes/L02_V007/257.jpg", "video": "L02_V007", "score": 0.3298952579498291}, {"frame_index": 60234, "path": "data/keyframes/L08_V003/260.jpg", "video": "L08_V003", "score": 0.32905256748199463}, {"frame_index": 56009, "path": "data/keyframes/L07_V019/097.jpg", "video": "L07_V019", "score": 0.32871460914611816}, {"frame_index": 37471, "path": "data/keyframes/L05_V016/174.jpg", "video": "L05_V016", "score": 0.3282276391983032}, {"frame_index": 92879, "path": "data/keyframes/L11_V017/149.jpg", "video": "L11_V017", "score": 0.3282022178173065}, {"frame_index": 9482, "path": "data/keyframes/L02_V005/242.jpg", "video": "L02_V005", "score": 0.32736527919769287}, {"frame_index": 10004, "path": "data/keyframes/L02_V007/263.jpg", "video": "L02_V007", "score": 0.32558584213256836}, {"frame_index": 26148, "path": "data/keyframes/L04_V005/298.jpg", "video": "L04_V005", "score": 0.3253779411315918}, {"frame_index": 104054, "path": "data/keyframes/L12_V022/276.jpg", "video": "L12_V022", "score": 0.32523825764656067}, {"frame_index": 13189, "path": "data/keyframes/L02_V019/246.jpg", "video": "L02_V019", "score": 0.3248705267906189}, {"frame_index": 3443, "path": "data/keyframes/L01_V014/129.jpg", "video": "L01_V014", "score": 0.32467755675315857}, {"frame_index": 102802, "path": "data/keyframes/L12_V018/392.jpg", "video": "L12_V018", "score": 0.3244481086730957}, {"frame_index": 102803, "path": "data/keyframes/L12_V018/393.jpg", "video": "L12_V018", "score": 0.32442808151245117}, {"frame_index": 25287, "path": "data/keyframes/L04_V002/286.jpg", "video": "L04_V002", "score": 0.3243354558944702}, {"frame_index": 4147, "path": "data/keyframes/L01_V017/126.jpg", "video": "L01_V017", "score": 0.32423728704452515}, {"frame_index": 77715, "path": "data/keyframes/L09_V029/127.jpg", "video": "L09_V029", "score": 0.3240615725517273}, {"frame_index": 82015, "path": "data/keyframes/L10_V011/387.jpg", "video": "L10_V011", "score": 0.32396188378334045}, {"frame_index": 61767, "path": "data/keyframes/L08_V008/298.jpg", "video": "L08_V008", "score": 0.323443204164505}, {"frame_index": 65020, "path": "data/keyframes/L08_V019/286.jpg", "video": "L08_V019", "score": 0.32337039709091187}, {"frame_index": 13913, "path": "data/keyframes/L02_V022/192.jpg", "video": "L02_V022", "score": 0.32325759530067444}, {"frame_index": 87669, "path": "data/keyframes/L10_V028/265.jpg", "video": "L10_V028", "score": 0.32281559705734253}, {"frame_index": 63264, "path": "data/keyframes/L08_V013/249.jpg", "video": "L08_V013", "score": 0.32260069251060486}, {"frame_index": 40598, "path": "data/keyframes/L05_V028/171.jpg", "video": "L05_V028", "score": 0.32258355617523193}, {"frame_index": 4548, "path": "data/keyframes/L01_V018/254.jpg", "video": "L01_V018", "score": 0.32214102149009705}, {"frame_index": 81973, "path": "data/keyframes/L10_V011/345.jpg", "video": "L10_V011", "score": 0.32202091813087463}, {"frame_index": 13714, "path": "data/keyframes/L02_V021/295.jpg", "video": "L02_V021", "score": 0.32180845737457275}, {"frame_index": 63263, "path": "data/keyframes/L08_V013/248.jpg", "video": "L08_V013", "score": 0.32169729471206665}, {"frame_index": 52285, "path": "data/keyframes/L07_V005/113.jpg", "video": "L07_V005", "score": 0.3215796649456024}, {"frame_index": 92619, "path": "data/keyframes/L11_V016/186.jpg", "video": "L11_V016", "score": 0.32138821482658386}, {"frame_index": 8922, "path": "data/keyframes/L02_V003/251.jpg", "video": "L02_V003", "score": 0.3210090398788452}, {"frame_index": 44406, "path": "data/keyframes/L06_V010/235.jpg", "video": "L06_V010", "score": 0.3209723234176636}, {"frame_index": 27933, "path": "data/keyframes/L04_V012/229.jpg", "video": "L04_V012", "score": 0.32084211707115173}, {"frame_index": 102799, "path": "data/keyframes/L12_V018/389.jpg", "video": "L12_V018", "score": 0.3202216327190399}, {"frame_index": 86729, "path": "data/keyframes/L10_V025/392.jpg", "video": "L10_V025", "score": 0.3199646472930908}, {"frame_index": 102789, "path": "data/keyframes/L12_V018/379.jpg", "video": "L12_V018", "score": 0.3197004497051239}, {"frame_index": 102797, "path": "data/keyframes/L12_V018/387.jpg", "video": "L12_V018", "score": 0.31967777013778687}, {"frame_index": 102786, "path": "data/keyframes/L12_V018/376.jpg", "video": "L12_V018", "score": 0.3195689618587494}, {"frame_index": 9972, "path": "data/keyframes/L02_V007/231.jpg", "video": "L02_V007", "score": 0.3194725215435028}, {"frame_index": 20513, "path": "data/keyframes/L03_V015/154.jpg", "video": "L03_V015", "score": 0.31935396790504456}]